yellowbox_statsd/__init__.py
yellowbox_statsd/_version.py
yellowbox_statsd/metrics.py
yellowbox_statsd/statsd.py
yellowbox_statsd-0.1.3.dist-info/LICENSE
yellowbox_statsd-0.1.3.dist-info/METADATA
yellowbox_statsd-0.1.3.dist-info/WHEEL
yellowbox_statsd-0.1.3.dist-info/RECORD
