Metadata-Version: 2.1
Name: yellowbox-statsd
Version: 0.1.3
Summary: 
License: MIT
Author: Biocatch LTD
Author-email: serverteam@biocatch.com
Requires-Python: >=3.8,<4.0
Classifier: License :: OSI Approved :: MIT License
Classifier: Programming Language :: Python :: 3
Classifier: Programming Language :: Python :: 3.8
Classifier: Programming Language :: Python :: 3.9
Classifier: Programming Language :: Python :: 3.10
Classifier: Programming Language :: Python :: 3.11
Classifier: Programming Language :: Python :: 3.12
Requires-Dist: yellowbox (>=0.7.0)
